buildme/__init__.py
buildme/cli.py
buildme/core.py
buildme/hfuncs.py
buildme-0.3.4.dist-info/LICENSE
buildme-0.3.4.dist-info/METADATA
buildme-0.3.4.dist-info/WHEEL
buildme-0.3.4.dist-info/entry_points.txt
buildme-0.3.4.dist-info/top_level.txt
buildme-0.3.4.dist-info/RECORD
