Metadata-Version: 2.1
Name: buildme
Version: 0.3.4
Summary: Yep, Its another build system
Home-page: https://github.com/Adwaith-Rajesh/buildme
Author: Adwaith Rajesh
Author-email: adwaithrajesh3180@gmail.com
License: MIT
Classifier: License :: OSI Approved :: MIT License
Classifier: Programming Language :: Python :: 3
Classifier: Programming Language :: Python :: 3 :: Only
Classifier: Programming Language :: Python :: 3.10
Classifier: Programming Language :: Python :: 3.11
Requires-Python: >=3.10.0
License-File: LICENSE
